DeepRad/__init__.py
DeepRad/main.py
DeepRad-1.0.0.dist-info/LICENSE.txt
DeepRad-1.0.0.dist-info/METADATA
DeepRad-1.0.0.dist-info/WHEEL
DeepRad-1.0.0.dist-info/top_level.txt
DeepRad-1.0.0.dist-info/RECORD
