Metadata-Version: 2.1
Name: DeepRad
Version: 1.0.0
Summary: A toolbox of Deep Learning in Medical Images
Home-page: https://github.com/mimrtl/DeepRad
Author: MIMRTL Lab
Author-email: mimrtl.uwmadison@gmail.com
License: UNKNOWN
Platform: UNKNOWN
Classifier: Programming Language :: Python :: 3
Classifier: License :: OSI Approved :: Apache Software License
Classifier: Operating System :: POSIX :: Linux
